napari_live_histogram/__init__.py
napari_live_histogram/_widget.py
napari_live_histogram/napari.yaml
napari_live_histogram/_tests/__init__.py
napari_live_histogram-0.0.2.dist-info/LICENSE
napari_live_histogram-0.0.2.dist-info/METADATA
napari_live_histogram-0.0.2.dist-info/WHEEL
napari_live_histogram-0.0.2.dist-info/entry_points.txt
napari_live_histogram-0.0.2.dist-info/top_level.txt
napari_live_histogram-0.0.2.dist-info/RECORD
